[
  {
    "Name": "henky",
    "TimeStarted": "2018-06-20T09:22:45.5687323+02:00",
    "TimeCompleted": "0001-01-01T00:00:00",
    "Score": 0
  },
  {
    "Name": "henk",
    "TimeStarted": "2018-06-20T09:34:47.1281656+02:00",
    "TimeCompleted": "2018-06-20T09:34:47.1291638+02:00",
    "Score": 0
  },
  {
    "Name": "bram",
    "TimeStarted": "2018-06-20T09:28:17.8413004+02:00",
    "TimeCompleted": "2018-06-20T09:28:53.6671553+02:00",
    "Score": 0
  },
  {
    "Name": "g",
    "TimeStarted": "2018-06-20T09:29:43.1459768+02:00",
    "TimeCompleted": "0001-01-01T00:00:00",
    "Score": 0
  },
  {
    "Name": "y",
    "TimeStarted": "2018-06-20T09:30:21.5449483+02:00",
    "TimeCompleted": "0001-01-01T00:00:00",
    "Score": 0
  },
  {
    "Name": "yy",
    "TimeStarted": "2018-06-20T09:30:31.4312357+02:00",
    "TimeCompleted": "0001-01-01T00:00:00",
    "Score": 0
  },
  {
    "Name": "h",
    "TimeStarted": "2018-06-20T09:33:01.2934838+02:00",
    "TimeCompleted": "2018-06-20T09:33:01.2934838+02:00",
    "Score": 0
  }
]